[{"id":"1","name":"\u4E2D\u7ACB\u57FA\u5730","type":"3","baselevel":"1","explain":"\u53EF\u88AB\u519B\u961F\u5360\u9886\u540E\u8FDB\u884C\u6539\u9020","skill":"\u5360\u9886\u540E\u53EF\u88AB\u6539\u9020","rad":"2.5","number":"1","target":"/","atkrange":"/","atk":"/","atkrate":"/","blood":"2000","price":"/","protime":"/","model":"ResourcePoint"},{"id":"2","name":"\u57FA\u5730","type":"0","baselevel":"1","explain":"","skill":"","rad":"2.5","number":"1","target":"1/2/3/0","atkrange":"5","atk":"200","atkrate":"1000","blood":"5000","price":"/","protime":"/","model":"Base"},{"id":"3","name":"\u70AE\u5854","type":"3","baselevel":"1","explain":"\u9632\u5FA1\u5854","skill":"\u4F1A\u5BF9\u8FDB\u5165\u5C04\u7A0B\u7684\u654C\u519B\u8FDB\u884C\u653B\u51FB","rad":"2.5","number":"1","target":"1/2/3/0","atkrange":"5","atk":"100","atkrate":"750","blood":"3000","price":"500","protime":"10000","model":"ResourceStation"},{"id":"4","name":"\u5E73\u5730","type":"3","baselevel":"1","explain":"\u65E0\u6CD5\u88AB\u653B\u51FB","skill":"","rad":"2.5","number":"1","target":"/","atkrange":"/","atk":"/","atkrate":"/","blood":"/","price":"/","protime":"/","model":"Resource"},{"id":"5","name":"\u9AD8\u7EA7\u57FA\u5730","type":"0","baselevel":"2","explain":"\u901A\u8FC7\u57FA\u5730\u5347\u7EA7\u540E\u5F62\u6210","skill":"","rad":"2.5","number":"1","target":"1/2/3/0","atkrange":"5","atk":"300","atkrate":"1000","blood":"8000","price":"100","protime":"/","model":"BaseUp"}]